odoo9_addon_stock_inventory_chatter-9.0.1.0.0-py2.7-nspkg.pth
odoo9_addon_stock_inventory_chatter-9.0.1.0.0.dist-info/DESCRIPTION.rst
odoo9_addon_stock_inventory_chatter-9.0.1.0.0.dist-info/METADATA
odoo9_addon_stock_inventory_chatter-9.0.1.0.0.dist-info/RECORD
odoo9_addon_stock_inventory_chatter-9.0.1.0.0.dist-info/WHEEL
odoo9_addon_stock_inventory_chatter-9.0.1.0.0.dist-info/metadata.json
odoo9_addon_stock_inventory_chatter-9.0.1.0.0.dist-info/namespace_packages.txt
odoo9_addon_stock_inventory_chatter-9.0.1.0.0.dist-info/top_level.txt
odoo_addons/stock_inventory_chatter/README.rst
odoo_addons/stock_inventory_chatter/__init__.py
odoo_addons/stock_inventory_chatter/__openerp__.py
odoo_addons/stock_inventory_chatter/data/stock_data.xml
odoo_addons/stock_inventory_chatter/models/__init__.py
odoo_addons/stock_inventory_chatter/models/stock.py
odoo_addons/stock_inventory_chatter/static/description/icon.png
odoo_addons/stock_inventory_chatter/views/stock_inventory_view.xml
